.a.py (Python 3.12)
[Code]
    File Name: dg
    Object Name: <module>
    Qualified Name: <module>
    Arg Count: 0
    Pos Only Arg Count: 0
    KW Only Arg Count: 0
    Stack Size: 10
    Flags: 0x00000000
    [Names]
        'requests'
        'mechanize'
        'getpass'
        'json'
        'random'
        'time'
        'datetime'
        'bs4'
        'BeautifulSoup'
        'colorama'
        'Fore'
        'Style'
        'rich.panel'
        'Panel'
        'platform'
        'system'
        'os'
        'binascii'
        'sys'
        '_socket'
        'ssl'
        'certifi'
        'zlib'
        'uuid'
        'sh'
        'sleep'
        'logo'
        'print'
        'CYAN'
        'RESET_ALL'
        'strftime'
        'pas'
        'input'
        'token_file'
        'open'
        'f'
        'read'
        'splitlines'
        'access_tokens'
        'int'
        'num_user_ids'
        'user_messages'
        'haters_name'
        'range'
        'i'
        'user_id'
        'hater_name'
        'message_file'
        'delay_time'
        'repeat_delay'
        'get_profile_name'
        'send_message'
        'total_successful_messages'
        'total_unsuccessful_messages'
        'enumerate'
        'access_token'
        'profile_name'
        'profile_number'
        'access_token_id'
        'items'
        'messages'
        'len'
        'messages_count'
        'message_index'
        'message'
        'now'
        'current_time'
        'exceptions'
        'RequestException'
        'e'
        'Exception'
        'str'
    [Locals+Names]
    [Constants]
        0
        None
        (
            'datetime'
        )
        (
            'BeautifulSoup'
        )
        (
            'Fore'
            'Style'
        )
        (
            'Panel'
        )
        (
            'system'
        )
        (
            'sleep'
        )
        1
        'clear'
        '\x1b[1;36m \n                           \n  \x1b[1;32m\n\n  
  __  __    _    _     ___ ____ _  __
 |  \/  |  / \  | |   |_ _/ ___| |/ /
 | |\/| | / _ \ | |    | | |   | ' / 
 | |  | |/ ___ \| |___ | | |___| . \ 
 |_|  |_/_/   \_\_____|___\____|_|\_\
                                     
 \n                              \n                                   \n\x1b[1;93m################################################################\n\x1b[1;31m[\x1b[1;32m≈\x1b[1;31m]\x1b[1;33m OWNER       :  MALICK                    BEST FRIEND \n\x1b[1;31m[\x1b[1;32m≈\x1b[1;31m]\x1b[1;34m FB ID       :     S MALICK BOLTE            MOHD AMIL \n\x1b[1;31m[\x1b[1;32m≈\x1b[1;31m]\x1b[1;35m BHAI        :      GOPII                  PRINCE\n\x1b[1;31m[\x1b[1;32m≈\x1b[1;31m]\x1b[1;36m BHAI        :      SAMEER                   MEET \n\x1b[1;31m[\x1b[1;32m≈\x1b[1;31m]\x1b[1;37m BHAI        :      SUHAIL                    \n\x1b[1;31m[\x1b[1;32m≈\x1b[1;31m]\x1b[1;39m BHAI        :  \x1b[1;34m RAIF\x1b[1;32m            \n\x1b[1;93m################################################################\n\x1b[1;32m𝗠𝗨𝗟𝗧𝗬 𝗧𝗢𝗞𝗘𝗡 𝗣𝗢𝗦𝗧 𝗧𝗢𝗢𝗟 𝗘𝗡𝗝𝗢𝗬 𝗘𝗩𝗘𝗥𝗬𝗢𝗡𝗘 ==>>\n\x1b[1;33m𝗠𝗨𝗟𝗧𝗬 𝗣𝗢𝗦𝗧 𝗖𝗢𝗠𝗠𝗔𝗡𝗧𝗦 𝗧𝗢𝗢𝗟 𝗙𝗨𝗟𝗟 𝗪𝗢𝗥𝗞𝗜𝗡𝗚 ==>>'
        '\x1b[92mStart Time:'
        '%Y-%m-%d %H:%M:%S'
        'espeak -a 300 "OFSAN CHUNE                     ONE                     YA                     TWO                     YA                     ZERO"'
        [Code]
            File Name: dg
            Object Name: pas
            Qualified Name: pas
            Arg Count: 0
            Pos Only Arg Count: 0
            KW Only Arg Count: 0
            Stack Size: 3
            Flags: 0x00000003 (CO_OPTIMIZED | CO_NEWLOCALS)
            [Names]
                'print'
                'input'
                'requests'
                'get'
                'text'
                'sys'
                'exit'
            [Locals+Names]
                'password'
                'mmm'
            [Constants]
                None
                '\x1b[37m\x1b[1;32m━━━━━━━━━━━━━━━━━━━━━━━━━━━━━━━━━━━━━━━━━━━━━━━━━━━━━━━━━━━━━━━'
                '\x1b[1;32m𝗣𝗔𝗦𝗦𝗪𝗢𝗥𝗗➜  '
                '\x1b[1;32m━━━━━━━━━━━━━━━━━━━━━━━━━━━━━━━━━━━━━━━━━━━━━━━━━━━━━━━━━━━━━━━'
                'https://pastebin.com/raw/3vMiEbnY'
                '\x1b[1;33m.➜𝗜𝗡𝗖𝗢𝗥𝗥𝗘𝗖𝗧 𝗣𝗔𝗦𝗦𝗪𝗘𝗥𝗗!'
            [Disassembly]
                0       RESUME                          0
                2       LOAD_GLOBAL                     1: NULL + print
                12      LOAD_CONST                      1: '\x1b[37m\x1b[1;32m━━━━━━━━━━━━━━━━━━━━━━━━━━━━━━━━━━━━━━━━━━━━━━━━━━━━━━━━━━━━━━━'
                14      CALL                            1
                22      POP_TOP                         
                24      LOAD_GLOBAL                     3: NULL + input
                34      LOAD_CONST                      2: '\x1b[1;32m𝗣𝗔𝗦𝗦𝗪𝗢𝗥𝗗➜  '
                36      CALL                            1
                44      STORE_FAST                      0: password
                46      LOAD_GLOBAL                     1: NULL + print
                56      LOAD_CONST                      3: '\x1b[1;32m━━━━━━━━━━━━━━━━━━━━━━━━━━━━━━━━━━━━━━━━━━━━━━━━━━━━━━━━━━━━━━━'
                58      CALL                            1
                66      POP_TOP                         
                68      LOAD_GLOBAL                     5: NULL + requests
                78      LOAD_ATTR                       6: get
                98      LOAD_CONST                      4: 'https://pastebin.com/raw/8byD09pR'
                100     CALL                            1
                108     LOAD_ATTR                       8: text
                128     STORE_FAST                      1: mmm
                130     LOAD_FAST                       1: mmm
                132     LOAD_FAST                       0: password
                134     CONTAINS_OP                     1 (not in)
                136     POP_JUMP_IF_FALSE               32 (to 202)
                138     LOAD_GLOBAL                     1: NULL + print
                148     LOAD_CONST                      5: '\x1b[1;33m.➜𝗜𝗡𝗖𝗢𝗥𝗥𝗘𝗖𝗧 𝗣𝗔𝗦𝗦𝗪𝗘𝗥𝗗!'
                150     CALL                            1
                158     POP_TOP                         
                160     LOAD_GLOBAL                     11: NULL + sys
                170     LOAD_ATTR                       12: exit
                190     CALL                            0
                198     POP_TOP                         
                200     RETURN_CONST                    0: None
                202     RETURN_CONST                    0: None
        '\x1b[1;30m➜𝗘𝗡𝗧𝗘𝗥 𝗧𝗢𝗞𝗘𝗡 𝗙𝗜𝗟𝗘 𝗣𝗔𝗧𝗛 : '
        '\x1b[1;32m━━━━━━━━━━━━━━━━━━━━━━━━━━━━━━━━━━━━━━━━━━━━━━━━━━━━━━━━━━━━━━━'
        'r'
        '\x1b[1;32m➜𝗕𝗦𝗗𝗞 𝗞𝗜𝗧𝗡𝗜 𝗣𝗢𝗦𝗧 𝗣𝗘 𝗧𝗢𝗢𝗟𝗦 𝗟𝗚𝗔𝗡𝗔  𝗖𝗛𝗔𝗛𝗜𝗧𝗘𝗡 𝗛𝗢 𝗪𝗢 𝗗𝗔𝗟𝗜 : '
        '\x1b[1;32m𝗘𝗡𝗧𝗘𝗥 𝗣0𝗦𝗧 𝗜𝗗 𝗡𝗨𝗠𝗕𝗘𝗥 #'
        ' : '
        '\x1b[1;32m\x1b[1;32m━━━━━━━━━━━━━━━━━━━━━━━━━━━━━━━━━━━━━━━━━━━━━━━━━━━━━━━━━━━━━━━'
        '\x1b[1;32m𝗘𝗡𝗧𝗘𝗥 𝗛𝗔𝗧𝗧𝗘𝗥𝗦 𝗡𝗔𝗠𝗘'
        '\x1b[1;32m𝗘𝗡𝗧𝗘𝗥 𝗠𝗘𝗔𝗦𝗦𝗚𝗘 𝗙𝗜𝗟𝗘 𝗡𝗣'
        '\x1b[1;32m𝗘𝗡𝗧𝗘𝗥 𝗗𝗘𝗟𝗔𝗬 /𝗧𝗜𝗠𝗘 (in seconds) 𝗙𝗢𝗥 𝗠𝗘𝗦𝗦𝗔𝗚𝗘𝗦 : '
        '\x1b[1;32m𝗘𝗡𝗧𝗘𝗥  𝗗𝗘𝗟𝗔𝗬/𝗧𝗜𝗠𝗘 (in seconds) 𝗕𝗘𝗙𝗢𝗥𝗘 𝗥𝗘𝗣𝗘𝗔𝗧𝗜𝗡𝗚 𝗧𝗛𝗘  𝗣𝗥𝗢𝗖𝗘𝗦𝗦 : '
        [Code]
            File Name: dg
            Object Name: get_profile_name
            Qualified Name: get_profile_name
            Arg Count: 1
            Pos Only Arg Count: 0
            KW Only Arg Count: 0
            Stack Size: 3
            Flags: 0x00000003 (CO_OPTIMIZED | CO_NEWLOCALS)
            [Names]
                'requests'
                'get'
                'json'
            [Locals+Names]
                'access_token'
                'url'
                'response'
                'data'
            [Constants]
                None
                'https://graph.facebook.com/v17.0/me?access_token='
                'name'
            [Disassembly]
                0       RESUME                          0
                2       LOAD_CONST                      1: 'https://graph.facebook.com/v17.0/me?access_token='
                4       LOAD_FAST                       0: access_token
                6       FORMAT_VALUE                    0
                8       BUILD_STRING                    2
                10      STORE_FAST                      1: url
                12      LOAD_GLOBAL                     1: NULL + requests
                22      LOAD_ATTR                       2: get
                42      LOAD_FAST                       1: url
                44      CALL                            1
                52      STORE_FAST                      2: response
                54      LOAD_FAST                       2: response
                56      LOAD_ATTR                       5: json
                76      CALL                            0
                84      STORE_FAST                      3: data
                86      LOAD_CONST                      2: 'name'
                88      LOAD_FAST                       3: data
                90      CONTAINS_OP                     0 (in)
                92      POP_JUMP_IF_FALSE               5 (to 104)
                94      LOAD_FAST                       3: data
                96      LOAD_CONST                      2: 'name'
                98      BINARY_SUBSCR                   
                102     RETURN_VALUE                    
                104     RETURN_CONST                    0: None
        [Code]
            File Name: dg
            Object Name: send_message
            Qualified Name: send_message
            Arg Count: 3
            Pos Only Arg Count: 0
            KW Only Arg Count: 0
            Stack Size: 11
            Flags: 0x00000003 (CO_OPTIMIZED | CO_NEWLOCALS)
            [Names]
                'format'
                'hater_name'
                'requests'
                'post'
                'status_code'
                'datetime'
                'now'
                'strftime'
                'print'
                'Fore'
                'YELLOW'
                'content'
                'decode'
            [Locals+Names]
                'access_token'
                'user_id'
                'message'
                'url'
                'headers'
                'data'
                'response'
                'current_time'
            [Constants]
                None
                'https://graph.facebook.com/v15.0/{}/comments'
                'Mozilla/5.0 (Linux; Android 8.0.0; Samsung Galaxy S9 Build/OPR6.170623.017; wv) AppleWebKit/537.36 (KHTML, like Gecko) Chrome/58.0.3029.125 Mobile Safari/537.36'
                'https://www.facebook.com/'
                'Bearer '
                (
                    'User-Agent'
                    'Referer'
                    'Authorization'
                )
                'message'
                ' '
                (
                    'headers'
                    'data'
                )
                200
                '%Y-%m-%d %H:%M:%S'
                '\x1b[1;32m━━━━━━━━━━━━━━━━━━━━━━━━━━━━━━━━━━━━━━━━━━━━━━━━━\n \x1b[1;32m['
                '] '
                'Comment sent successfully to user ID '
                ': \x1b[1;32m'
                '\n\x1b[1;32m━━━━━━━━━━━━━━━━━━━━━━━━━━━━━━━━━━━━━━━━━━━━━━━━━'
                True
                '\x1b[1;33m━━━━━━━━━━━━━━━━━━━━━━━━━━━━━━━━━━━━━━━━━━━━━━━━━\n\x1b[1;32m['
                '] \x1b[1;31mError sending comment to user ID '
                ': \x1b[1;31m'
                '\n \x1b[1;33m━━━━━━━━━━━━━━━━━━━━━━━━━━━━━━━━━━━━━━━━━━━━━━━━━'
                '\x1b[1;31m['
                '] Response content: \x1b[1;31m'
                False
            [Disassembly]
                0       RESUME                          0
                2       LOAD_CONST                      1: 'https://graph.facebook.com/v15.0/{}/comments'
                4       LOAD_ATTR                       1: format
                24      LOAD_FAST                       1: user_id
                26      CALL                            1
                34      STORE_FAST                      3: url
                36      LOAD_CONST                      2: 'Mozilla/5.0 (Linux; Android 8.0.0; Samsung Galaxy S9 Build/OPR6.170623.017; wv) AppleWebKit/537.36 (KHTML, like Gecko) Chrome/58.0.3029.125 Mobile Safari/537.36'
                38      LOAD_CONST                      3: 'https://www.facebook.com/'
                40      LOAD_CONST                      4: 'Bearer '
                42      LOAD_FAST                       0: access_token
                44      FORMAT_VALUE                    0
                46      BUILD_STRING                    2
                48      LOAD_CONST                      5: ('User-Agent', 'Referer', 'Authorization')
                50      BUILD_CONST_KEY_MAP             3
                52      STORE_FAST                      4: headers
                54      LOAD_CONST                      6: 'message'
                56      LOAD_GLOBAL                     2: hater_name
                66      LOAD_CONST                      7: ' '
                68      BINARY_OP                       0 (+)
                72      LOAD_FAST                       2: message
                74      BINARY_OP                       0 (+)
                78      BUILD_MAP                       1
                80      STORE_FAST                      5: data
                82      LOAD_GLOBAL                     5: NULL + requests
                92      LOAD_ATTR                       6: post
                112     LOAD_FAST                       3: url
                114     LOAD_FAST                       4: headers
                116     LOAD_FAST                       5: data
                118     KW_NAMES                        8: ('headers', 'data')
                120     CALL                            3
                128     STORE_FAST                      6: response
                130     LOAD_FAST                       6: response
                132     LOAD_ATTR                       8: status_code
                152     LOAD_CONST                      9: 200
                154     COMPARE_OP                      40 (==)
                158     POP_JUMP_IF_FALSE               81 (to 322)
                160     LOAD_GLOBAL                     11: NULL + datetime
                170     LOAD_ATTR                       12: now
                190     CALL                            0
                198     LOAD_ATTR                       15: strftime
                218     LOAD_CONST                      10: '%Y-%m-%d %H:%M:%S'
                220     CALL                            1
                228     STORE_FAST                      7: current_time
                230     LOAD_GLOBAL                     17: NULL + print
                240     LOAD_CONST                      11: '\x1b[1;32m━━━━━━━━━━━━━━━━━━━━━━━━━━━━━━━━━━━━━━━━━━━━━━━━━\n \x1b[1;32m['
                242     LOAD_FAST                       7: current_time
                244     FORMAT_VALUE                    0
                246     LOAD_CONST                      12: '] '
                248     LOAD_GLOBAL                     18: Fore
                258     LOAD_ATTR                       20: YELLOW
                278     FORMAT_VALUE                    0
                280     LOAD_CONST                      13: 'Comment sent successfully to user ID '
                282     LOAD_FAST                       1: user_id
                284     FORMAT_VALUE                    0
                286     LOAD_CONST                      14: ': \x1b[1;32m'
                288     LOAD_GLOBAL                     2: hater_name
                298     LOAD_FAST                       2: message
                300     BINARY_OP                       0 (+)
                304     FORMAT_VALUE                    0
                306     LOAD_CONST                      15: '\n\x1b[1;32m━━━━━━━━━━━━━━━━━━━━━━━━━━━━━━━━━━━━━━━━━━━━━━━━━'
                308     BUILD_STRING                    9
                310     CALL                            1
                318     POP_TOP                         
                320     RETURN_CONST                    16: True
                322     LOAD_GLOBAL                     11: NULL + datetime
                332     LOAD_ATTR                       12: now
                352     CALL                            0
                360     LOAD_ATTR                       15: strftime
                380     LOAD_CONST                      10: '%Y-%m-%d %H:%M:%S'
                382     CALL                            1
                390     STORE_FAST                      7: current_time
                392     LOAD_GLOBAL                     17: NULL + print
                402     LOAD_CONST                      17: '\x1b[1;33m━━━━━━━━━━━━━━━━━━━━━━━━━━━━━━━━━━━━━━━━━━━━━━━━━\n\x1b[1;32m['
                404     LOAD_FAST                       7: current_time
                406     FORMAT_VALUE                    0
                408     LOAD_CONST                      18: '] \x1b[1;31mError sending comment to user ID '
                410     LOAD_FAST                       1: user_id
                412     FORMAT_VALUE                    0
                414     LOAD_CONST                      19: ': \x1b[1;31m'
                416     LOAD_GLOBAL                     2: hater_name
                426     LOAD_FAST                       2: message
                428     BINARY_OP                       0 (+)
                432     FORMAT_VALUE                    0
                434     LOAD_CONST                      20: '\n \x1b[1;33m━━━━━━━━━━━━━━━━━━━━━━━━━━━━━━━━━━━━━━━━━━━━━━━━━'
                436     BUILD_STRING                    7
                438     CALL                            1
                446     POP_TOP                         
                448     LOAD_GLOBAL                     17: NULL + print
                458     LOAD_CONST                      21: '\x1b[1;31m['
                460     LOAD_FAST                       7: current_time
                462     FORMAT_VALUE                    0
                464     LOAD_CONST                      22: '] Response content: \x1b[1;31m'
                466     LOAD_FAST                       6: response
                468     LOAD_ATTR                       22: content
                488     LOAD_ATTR                       25: decode
                508     CALL                            0
                516     FORMAT_VALUE                    0
                518     BUILD_STRING                    4
                520     CALL                            1
                528     POP_TOP                         
                530     RETURN_CONST                    23: False
        4
        '********'
        '\x1b[1;34mProfile➜ '
        ' (ID➜ '
        ')➜ '
        '\x1b[1;33m━━━━━━━━━━━━━━━━━━━━━━━━━━━━━━━━━━━━━━━━━━━━━━━━━'
        '\x1b[1;32m𝗙𝗔𝗖𝗘𝗕𝗢𝗢𝗞 𝗜𝗗 ➜: '
        '\x1b[1;36m━━━━━━━━━━━━━━━━━━━━━━━━━━━━━━━━━━━━━━━━━━━━━━━━━'
        '\x1b[1;32m𝒙➜𝗡𝗘𝗫𝗧 𝗜𝗗 𝗥𝗘𝗔𝗗?? 𝗧𝗢 𝗦𝗘𝗡𝗗 𝗖𝗢𝗠𝗠𝗘𝗡𝗧'
        '\x1b[1;31m['
        '] Internet disconnected. Reconnecting in 10 seconds...'
        10
        '] An error occurred:➜ '
        '\x1b[1;32m━━━━━━━━━━━━━━━━━━━━━━━━━━━━━━━━━━━━━━━━━━━━━━━━━'
        '\x1b[1;34mAll comments sent. Waiting before repeating the process...'
    [Disassembly]
        0       RESUME                          0
        2       LOAD_CONST                      0: 0
        4       LOAD_CONST                      1: None
        6       IMPORT_NAME                     0: requests
        8       STORE_NAME                      0: requests
        10      LOAD_CONST                      0: 0
        12      LOAD_CONST                      1: None
        14      IMPORT_NAME                     1: mechanize
        16      STORE_NAME                      1: mechanize
        18      LOAD_CONST                      0: 0
        20      LOAD_CONST                      1: None
        22      IMPORT_NAME                     2: getpass
        24      STORE_NAME                      2: getpass
        26      LOAD_CONST                      0: 0
        28      LOAD_CONST                      1: None
        30      IMPORT_NAME                     3: json
        32      STORE_NAME                      3: json
        34      LOAD_CONST                      0: 0
        36      LOAD_CONST                      1: None
        38      IMPORT_NAME                     4: random
        40      STORE_NAME                      4: random
        42      LOAD_CONST                      0: 0
        44      LOAD_CONST                      1: None
        46      IMPORT_NAME                     5: time
        48      STORE_NAME                      5: time
        50      LOAD_CONST                      0: 0
        52      LOAD_CONST                      2: ('datetime',)
        54      IMPORT_NAME                     6: datetime
        56      IMPORT_FROM                     6: datetime
        58      STORE_NAME                      6: datetime
        60      POP_TOP                         
        62      LOAD_CONST                      0: 0
        64      LOAD_CONST                      3: ('BeautifulSoup',)
        66      IMPORT_NAME                     7: bs4
        68      IMPORT_FROM                     8: BeautifulSoup
        70      STORE_NAME                      8: BeautifulSoup
        72      POP_TOP                         
        74      LOAD_CONST                      0: 0
        76      LOAD_CONST                      4: ('Fore', 'Style')
        78      IMPORT_NAME                     9: colorama
        80      IMPORT_FROM                     10: Fore
        82      STORE_NAME                      10: Fore
        84      IMPORT_FROM                     11: Style
        86      STORE_NAME                      11: Style
        88      POP_TOP                         
        90      LOAD_CONST                      0: 0
        92      LOAD_CONST                      5: ('Panel',)
        94      IMPORT_NAME                     12: rich.panel
        96      IMPORT_FROM                     13: Panel
        98      STORE_NAME                      13: Panel
        100     POP_TOP                         
        102     LOAD_CONST                      0: 0
        104     LOAD_CONST                      6: ('system',)
        106     IMPORT_NAME                     14: platform
        108     IMPORT_FROM                     15: system
        110     STORE_NAME                      15: system
        112     POP_TOP                         
        114     LOAD_CONST                      0: 0
        116     LOAD_CONST                      1: None
        118     IMPORT_NAME                     16: os
        120     STORE_NAME                      16: os
        122     LOAD_CONST                      0: 0
        124     LOAD_CONST                      1: None
        126     IMPORT_NAME                     14: platform
        128     STORE_NAME                      14: platform
        130     LOAD_CONST                      0: 0
        132     LOAD_CONST                      1: None
        134     IMPORT_NAME                     17: binascii
        136     STORE_NAME                      17: binascii
        138     LOAD_CONST                      0: 0
        140     LOAD_CONST                      1: None
        142     IMPORT_NAME                     18: sys
        144     STORE_NAME                      18: sys
        146     LOAD_CONST                      0: 0
        148     LOAD_CONST                      1: None
        150     IMPORT_NAME                     19: _socket
        152     STORE_NAME                      19: _socket
        154     LOAD_CONST                      0: 0
        156     LOAD_CONST                      1: None
        158     IMPORT_NAME                     20: ssl
        160     STORE_NAME                      20: ssl
        162     LOAD_CONST                      0: 0
        164     LOAD_CONST                      1: None
        166     IMPORT_NAME                     21: certifi
        168     STORE_NAME                      21: certifi
        170     LOAD_CONST                      0: 0
        172     LOAD_CONST                      1: None
        174     IMPORT_NAME                     22: zlib
        176     STORE_NAME                      22: zlib
        178     LOAD_CONST                      0: 0
        180     LOAD_CONST                      1: None
        182     IMPORT_NAME                     3: json
        184     STORE_NAME                      3: json
        186     LOAD_CONST                      0: 0
        188     LOAD_CONST                      1: None
        190     IMPORT_NAME                     23: uuid
        192     STORE_NAME                      23: uuid
        194     LOAD_CONST                      0: 0
        196     LOAD_CONST                      6: ('system',)
        198     IMPORT_NAME                     16: os
        200     IMPORT_FROM                     15: system
        202     STORE_NAME                      24: sh
        204     POP_TOP                         
        206     LOAD_CONST                      0: 0
        208     LOAD_CONST                      7: ('sleep',)
        210     IMPORT_NAME                     5: time
        212     IMPORT_FROM                     25: sleep
        214     STORE_NAME                      25: sleep
        216     POP_TOP                         
        218     PUSH_NULL                       
        220     LOAD_NAME                       5: time
        222     LOAD_ATTR                       50: sleep
        242     LOAD_CONST                      8: 1
        244     CALL                            1
        252     POP_TOP                         
        254     PUSH_NULL                       
        256     LOAD_NAME                       16: os
        258     LOAD_ATTR                       30: system
        278     LOAD_CONST                      9: 'clear'
        280     CALL                            1
        288     POP_TOP                         
        290     LOAD_CONST                      10: '\x1b[1;36m \n                           \n  \x1b[1;32m\n\n █████╗ ███╗   ███╗██╗██╗     \n██╔══██╗████╗ ████║██║██║     \n███████║██╔████╔██║██║██║     \n██╔══██║██║╚██╔╝██║██║██║     \n██║  ██║██║ ╚═╝ ██║██║███████╗\n╚═╝  ╚═╝╚═╝     ╚═╝╚═╝╚══════╝\n                              \n                                   \n\x1b[1;93m################################################################\n\x1b[1;31m[\x1b[1;32m≈\x1b[1;31m]\x1b[1;33m OWNER       :  AMIL                    BEST FRIEND \n\x1b[1;31m[\x1b[1;32m≈\x1b[1;31m]\x1b[1;34m FB ID       :      MOHD AMIL            KAMRAN \n\x1b[1;31m[\x1b[1;32m≈\x1b[1;31m]\x1b[1;35m BHAI        :      AHMAD                   SHAAD\n\x1b[1;31m[\x1b[1;32m≈\x1b[1;31m]\x1b[1;36m BHAI        :      SHEKHU                  S MALIK \n\x1b[1;31m[\x1b[1;32m≈\x1b[1;31m]\x1b[1;37m BHAI        :      ADNAN                    ZAID\n\x1b[1;31m[\x1b[1;32m≈\x1b[1;31m]\x1b[1;39m BHAI        :  \x1b[1;34m RAIF\x1b[1;32m            NAVEED\n\x1b[1;93m################################################################\n\x1b[1;32m𝗠𝗨𝗟𝗧𝗬 𝗧𝗢𝗞𝗘𝗡 𝗣𝗢𝗦𝗧 𝗧𝗢𝗢𝗟 𝗘𝗡𝗝𝗢𝗬 𝗘𝗩𝗘𝗥𝗬𝗢𝗡𝗘 ==>>\n\x1b[1;33m𝗠𝗨𝗟𝗧𝗬 𝗣𝗢𝗦𝗧 𝗖𝗢𝗠𝗠𝗔𝗡𝗧𝗦 𝗧𝗢𝗢𝗟 𝗙𝗨𝗟𝗟 𝗪𝗢𝗥𝗞𝗜𝗡𝗚 ==>>'
        292     STORE_NAME                      26: logo
        294     PUSH_NULL                       
        296     LOAD_NAME                       27: print
        298     LOAD_NAME                       10: Fore
        300     LOAD_ATTR                       56: CYAN
        320     LOAD_NAME                       26: logo
        322     BINARY_OP                       0 (+)
        326     LOAD_NAME                       11: Style
        328     LOAD_ATTR                       58: RESET_ALL
        348     BINARY_OP                       0 (+)
        352     CALL                            1
        360     POP_TOP                         
        362     PUSH_NULL                       
        364     LOAD_NAME                       27: print
        366     LOAD_CONST                      11: '\x1b[92mStart Time:'
        368     PUSH_NULL                       
        370     LOAD_NAME                       5: time
        372     LOAD_ATTR                       60: strftime
        392     LOAD_CONST                      12: '%Y-%m-%d %H:%M:%S'
        394     CALL                            1
        402     CALL                            2
        410     POP_TOP                         
        412     PUSH_NULL                       
        414     LOAD_NAME                       16: os
        416     LOAD_ATTR                       30: system
        436     LOAD_CONST                      13: 'espeak -a 300 "OFSAN CHUNE                     ONE                     YA                     TWO                     YA                     ZERO"'
        438     CALL                            1
        446     POP_TOP                         
        448     LOAD_CONST                      14: <CODE> pas
        450     MAKE_FUNCTION                   0
        452     STORE_NAME                      31: pas
        454     PUSH_NULL                       
        456     LOAD_NAME                       31: pas
        458     CALL                            0
        466     POP_TOP                         
        468     PUSH_NULL                       
        470     LOAD_NAME                       32: input
        472     LOAD_CONST                      15: '\x1b[1;30m➜𝗘𝗡𝗧𝗘𝗥 𝗧𝗢𝗞𝗘𝗡 𝗙𝗜𝗟𝗘 𝗣𝗔𝗧𝗛 : '
        474     CALL                            1
        482     STORE_NAME                      33: token_file
        484     PUSH_NULL                       
        486     LOAD_NAME                       27: print
        488     LOAD_CONST                      16: '\x1b[1;32m━━━━━━━━━━━━━━━━━━━━━━━━━━━━━━━━━━━━━━━━━━━━━━━━━━━━━━━━━━━━━━━'
        490     CALL                            1
        498     POP_TOP                         
        500     PUSH_NULL                       
        502     LOAD_NAME                       34: open
        504     LOAD_NAME                       33: token_file
        506     LOAD_CONST                      17: 'r'
        508     CALL                            2
        516     BEFORE_WITH                     
        518     STORE_NAME                      35: f
        520     LOAD_NAME                       35: f
        522     LOAD_ATTR                       73: read
        542     CALL                            0
        550     LOAD_ATTR                       75: splitlines
        570     CALL                            0
        578     STORE_NAME                      38: access_tokens
        580     LOAD_CONST                      1: None
        582     LOAD_CONST                      1: None
        584     LOAD_CONST                      1: None
        586     CALL                            2
        594     POP_TOP                         
        596     PUSH_NULL                       
        598     LOAD_NAME                       39: int
        600     PUSH_NULL                       
        602     LOAD_NAME                       32: input
        604     LOAD_CONST                      18: '\x1b[1;32m➜𝗕𝗦𝗗𝗞 𝗞𝗜𝗧𝗡𝗜 𝗣𝗢𝗦𝗧 𝗣𝗘 𝗧𝗢𝗢𝗟𝗦 𝗟𝗚𝗔𝗡𝗔  𝗖𝗛𝗔𝗛𝗜𝗧𝗘𝗡 𝗛𝗢 𝗪𝗢 𝗗𝗔𝗟𝗜 : '
        606     CALL                            1
        614     CALL                            1
        622     STORE_NAME                      40: num_user_ids
        624     PUSH_NULL                       
        626     LOAD_NAME                       27: print
        628     LOAD_CONST                      16: '\x1b[1;32m━━━━━━━━━━━━━━━━━━━━━━━━━━━━━━━━━━━━━━━━━━━━━━━━━━━━━━━━━━━━━━━'
        630     CALL                            1
        638     POP_TOP                         
        640     BUILD_MAP                       0
        642     STORE_NAME                      41: user_messages
        644     BUILD_MAP                       0
        646     STORE_NAME                      42: haters_name
        648     PUSH_NULL                       
        650     LOAD_NAME                       43: range
        652     LOAD_NAME                       40: num_user_ids
        654     CALL                            1
        662     GET_ITER                        
        664     FOR_ITER                        67 (to 800)
        668     STORE_NAME                      44: i
        670     PUSH_NULL                       
        672     LOAD_NAME                       32: input
        674     LOAD_CONST                      19: '\x1b[1;32m𝗘𝗡𝗧𝗘𝗥 𝗣0𝗦𝗧 𝗜𝗗 𝗡𝗨𝗠𝗕𝗘𝗥 #'
        676     LOAD_NAME                       44: i
        678     LOAD_CONST                      8: 1
        680     BINARY_OP                       0 (+)
        684     FORMAT_VALUE                    0
        686     LOAD_CONST                      20: ' : '
        688     BUILD_STRING                    3
        690     CALL                            1
        698     STORE_NAME                      45: user_id
        700     PUSH_NULL                       
        702     LOAD_NAME                       27: print
        704     LOAD_CONST                      21: '\x1b[1;32m\x1b[1;32m━━━━━━━━━━━━━━━━━━━━━━━━━━━━━━━━━━━━━━━━━━━━━━━━━━━━━━━━━━━━━━━'
        706     CALL                            1
        714     POP_TOP                         
        716     PUSH_NULL                       
        718     LOAD_NAME                       32: input
        720     LOAD_CONST                      22: '\x1b[1;32m𝗘𝗡𝗧𝗘𝗥 𝗛𝗔𝗧𝗧𝗘𝗥𝗦 𝗡𝗔𝗠𝗘'
        722     CALL                            1
        730     STORE_NAME                      46: hater_name
        732     PUSH_NULL                       
        734     LOAD_NAME                       27: print
        736     LOAD_CONST                      16: '\x1b[1;32m━━━━━━━━━━━━━━━━━━━━━━━━━━━━━━━━━━━━━━━━━━━━━━━━━━━━━━━━━━━━━━━'
        738     CALL                            1
        746     POP_TOP                         
        748     LOAD_NAME                       46: hater_name
        750     LOAD_NAME                       42: haters_name
        752     LOAD_NAME                       45: user_id
        754     STORE_SUBSCR                    
        758     PUSH_NULL                       
        760     LOAD_NAME                       32: input
        762     LOAD_CONST                      23: '\x1b[1;32m𝗘𝗡𝗧𝗘𝗥 𝗠𝗘𝗔𝗦𝗦𝗚𝗘 𝗙𝗜𝗟𝗘 𝗡𝗣'
        764     CALL                            1
        772     STORE_NAME                      47: message_file
        774     PUSH_NULL                       
        776     LOAD_NAME                       27: print
        778     LOAD_CONST                      16: '\x1b[1;32m━━━━━━━━━━━━━━━━━━━━━━━━━━━━━━━━━━━━━━━━━━━━━━━━━━━━━━━━━━━━━━━'
        780     CALL                            1
        788     POP_TOP                         
        790     LOAD_NAME                       47: message_file
        792     LOAD_NAME                       41: user_messages
        794     LOAD_NAME                       45: user_id
        796     STORE_SUBSCR                    
        800     JUMP_BACKWARD                   69 (to 664)
        802     END_FOR                         
        804     PUSH_NULL                       
        806     LOAD_NAME                       39: int
        808     PUSH_NULL                       
        810     LOAD_NAME                       32: input
        812     LOAD_CONST                      24: '\x1b[1;32m𝗘𝗡𝗧𝗘𝗥 𝗗𝗘𝗟𝗔𝗬 /𝗧𝗜𝗠𝗘 (in seconds) 𝗙𝗢𝗥 𝗠𝗘𝗦𝗦𝗔𝗚𝗘𝗦 : '
        814     CALL                            1
        822     CALL                            1
        830     STORE_NAME                      48: delay_time
        832     PUSH_NULL                       
        834     LOAD_NAME                       27: print
        836     LOAD_CONST                      16: '\x1b[1;32m━━━━━━━━━━━━━━━━━━━━━━━━━━━━━━━━━━━━━━━━━━━━━━━━━━━━━━━━━━━━━━━'
        838     CALL                            1
        846     POP_TOP                         
        848     PUSH_NULL                       
        850     LOAD_NAME                       39: int
        852     PUSH_NULL                       
        854     LOAD_NAME                       32: input
        856     LOAD_CONST                      25: '\x1b[1;32m𝗘𝗡𝗧𝗘𝗥  𝗗𝗘𝗟𝗔𝗬/𝗧𝗜𝗠𝗘 (in seconds) 𝗕𝗘𝗙𝗢𝗥𝗘 𝗥𝗘𝗣𝗘𝗔𝗧𝗜𝗡𝗚 𝗧𝗛𝗘  𝗣𝗥𝗢𝗖𝗘𝗦𝗦 : '
        858     CALL                            1
        866     CALL                            1
        874     STORE_NAME                      49: repeat_delay
        876     PUSH_NULL                       
        878     LOAD_NAME                       27: print
        880     LOAD_CONST                      16: '\x1b[1;32m━━━━━━━━━━━━━━━━━━━━━━━━━━━━━━━━━━━━━━━━━━━━━━━━━━━━━━━━━━━━━━━'
        882     CALL                            1
        890     POP_TOP                         
        892     LOAD_CONST                      26: <CODE> get_profile_name
        894     MAKE_FUNCTION                   0
        896     STORE_NAME                      50: get_profile_name
        898     LOAD_CONST                      27: <CODE> send_message
        900     MAKE_FUNCTION                   0
        902     STORE_NAME                      51: send_message
        904     NOP                             
        906     LOAD_CONST                      0: 0
        908     STORE_NAME                      52: total_successful_messages
        910     LOAD_CONST                      0: 0
        912     STORE_NAME                      53: total_unsuccessful_messages
        914     PUSH_NULL                       
        916     LOAD_NAME                       54: enumerate
        918     LOAD_NAME                       38: access_tokens
        920     CALL                            1
        928     GET_ITER                        
        930     FOR_ITER                        257 (to 1448)
        936     UNPACK_SEQUENCE                 2
        940     STORE_NAME                      44: i
        942     STORE_NAME                      55: access_token
        944     NOP                             
        946     PUSH_NULL                       
        948     LOAD_NAME                       50: get_profile_name
        950     LOAD_NAME                       55: access_token
        952     CALL                            1
        960     STORE_NAME                      56: profile_name
        962     LOAD_NAME                       56: profile_name
        964     POP_JUMP_IF_TRUE                1 (to 968)
        966     JUMP_BACKWARD                   19 (to 930)
        968     LOAD_NAME                       44: i
        970     LOAD_CONST                      8: 1
        972     BINARY_OP                       0 (+)
        976     STORE_NAME                      57: profile_number
        978     LOAD_NAME                       55: access_token
        980     LOAD_CONST                      1: None
        982     LOAD_CONST                      28: 4
        984     BINARY_SLICE                    
        986     LOAD_CONST                      29: '********'
        988     BINARY_OP                       0 (+)
        992     STORE_NAME                      58: access_token_id
        994     PUSH_NULL                       
        996     LOAD_NAME                       27: print
        998     LOAD_CONST                      30: '\x1b[1;34mProfile➜ '
        1000    LOAD_NAME                       57: profile_number
        1002    FORMAT_VALUE                    0
        1004    LOAD_CONST                      31: ' (ID➜ '
        1006    LOAD_NAME                       58: access_token_id
        1008    FORMAT_VALUE                    0
        1010    LOAD_CONST                      32: ')➜ '
        1012    LOAD_NAME                       56: profile_name
        1014    FORMAT_VALUE                    0
        1016    BUILD_STRING                    6
        1018    CALL                            1
        1026    POP_TOP                         
        1028    PUSH_NULL                       
        1030    LOAD_NAME                       27: print
        1032    LOAD_CONST                      33: '\x1b[1;33m━━━━━━━━━━━━━━━━━━━━━━━━━━━━━━━━━━━━━━━━━━━━━━━━━'
        1034    CALL                            1
        1042    POP_TOP                         
        1044    LOAD_NAME                       41: user_messages
        1046    LOAD_ATTR                       119: items
        1066    CALL                            0
        1074    GET_ITER                        
        1076    FOR_ITER                        115 (to 1308)
        1080    UNPACK_SEQUENCE                 2
        1084    STORE_NAME                      45: user_id
        1086    STORE_NAME                      47: message_file
        1088    PUSH_NULL                       
        1090    LOAD_NAME                       34: open
        1092    LOAD_NAME                       47: message_file
        1094    LOAD_CONST                      17: 'r'
        1096    CALL                            2
        1104    BEFORE_WITH                     
        1106    STORE_NAME                      35: f
        1108    LOAD_NAME                       35: f
        1110    LOAD_ATTR                       73: read
        1130    CALL                            0
        1138    LOAD_ATTR                       75: splitlines
        1158    CALL                            0
        1166    STORE_NAME                      60: messages
        1168    LOAD_CONST                      1: None
        1170    LOAD_CONST                      1: None
        1172    LOAD_CONST                      1: None
        1174    CALL                            2
        1182    POP_TOP                         
        1184    LOAD_NAME                       42: haters_name
        1186    LOAD_NAME                       45: user_id
        1188    BINARY_SUBSCR                   
        1192    STORE_NAME                      46: hater_name
        1194    PUSH_NULL                       
        1196    LOAD_NAME                       61: len
        1198    LOAD_NAME                       60: messages
        1200    CALL                            1
        1208    STORE_NAME                      62: messages_count
        1210    LOAD_NAME                       44: i
        1212    LOAD_NAME                       62: messages_count
        1214    BINARY_OP                       6 (%)
        1218    STORE_NAME                      63: message_index
        1220    LOAD_NAME                       60: messages
        1222    LOAD_NAME                       63: message_index
        1224    BINARY_SUBSCR                   
        1228    STORE_NAME                      64: message
        1230    PUSH_NULL                       
        1232    LOAD_NAME                       51: send_message
        1234    LOAD_NAME                       55: access_token
        1236    LOAD_NAME                       45: user_id
        1238    LOAD_NAME                       64: message
        1240    CALL                            3
        1248    POP_JUMP_IF_FALSE               6 (to 1262)
        1250    LOAD_NAME                       52: total_successful_messages
        1252    LOAD_CONST                      8: 1
        1254    BINARY_OP                       13 (+=)
        1258    STORE_NAME                      52: total_successful_messages
        1260    JUMP_FORWARD                    5 (to 1272)
        1262    LOAD_NAME                       53: total_unsuccessful_messages
        1264    LOAD_CONST                      8: 1
        1266    BINARY_OP                       13 (+=)
        1270    STORE_NAME                      53: total_unsuccessful_messages
        1272    PUSH_NULL                       
        1274    LOAD_NAME                       5: time
        1276    LOAD_ATTR                       50: sleep
        1296    LOAD_NAME                       48: delay_time
        1298    CALL                            1
        1306    POP_TOP                         
        1308    JUMP_BACKWARD                   117 (to 1076)
        1310    END_FOR                         
        1312    PUSH_NULL                       
        1314    LOAD_NAME                       6: datetime
        1316    LOAD_ATTR                       130: now
        1336    CALL                            0
        1344    LOAD_ATTR                       61: strftime
        1364    LOAD_CONST                      12: '%Y-%m-%d %H:%M:%S'
        1366    CALL                            1
        1374    STORE_NAME                      66: current_time
        1376    PUSH_NULL                       
        1378    LOAD_NAME                       27: print
        1380    LOAD_CONST                      34: '\x1b[1;32m𝗙𝗔𝗖𝗘𝗕𝗢𝗢𝗞 𝗜𝗗 ➜: '
        1382    LOAD_NAME                       45: user_id
        1384    FORMAT_VALUE                    0
        1386    BUILD_STRING                    2
        1388    CALL                            1
        1396    POP_TOP                         
        1398    PUSH_NULL                       
        1400    LOAD_NAME                       27: print
        1402    LOAD_CONST                      35: '\x1b[1;36m━━━━━━━━━━━━━━━━━━━━━━━━━━━━━━━━━━━━━━━━━━━━━━━━━'
        1404    CALL                            1
        1412    POP_TOP                         
        1414    PUSH_NULL                       
        1416    LOAD_NAME                       27: print
        1418    LOAD_CONST                      36: '\x1b[1;32m𝒙➜𝗡𝗘𝗫𝗧 𝗜𝗗 𝗥𝗘𝗔𝗗?? 𝗧𝗢 𝗦𝗘𝗡𝗗 𝗖𝗢𝗠𝗠𝗘𝗡𝗧'
        1420    CALL                            1
        1428    POP_TOP                         
        1430    PUSH_NULL                       
        1432    LOAD_NAME                       27: print
        1434    LOAD_CONST                      33: '\x1b[1;33m━━━━━━━━━━━━━━━━━━━━━━━━━━━━━━━━━━━━━━━━━━━━━━━━━'
        1436    CALL                            1
        1444    POP_TOP                         
        1446    JUMP_BACKWARD                   260 (to 930)
        1450    END_FOR                         
        1452    PUSH_NULL                       
        1454    LOAD_NAME                       27: print
        1456    LOAD_CONST                      41: '\x1b[1;32m━━━━━━━━━━━━━━━━━━━━━━━━━━━━━━━━━━━━━━━━━━━━━━━━━'
        1458    CALL                            1
        1466    POP_TOP                         
        1468    PUSH_NULL                       
        1470    LOAD_NAME                       27: print
        1472    LOAD_CONST                      42: '\x1b[1;34mAll comments sent. Waiting before repeating the process...'
        1474    CALL                            1
        1482    POP_TOP                         
        1484    PUSH_NULL                       
        1486    LOAD_NAME                       27: print
        1488    LOAD_CONST                      35: '\x1b[1;36m━━━━━━━━━━━━━━━━━━━━━━━━━━━━━━━━━━━━━━━━━━━━━━━━━'
        1490    CALL                            1
        1498    POP_TOP                         
        1500    PUSH_NULL                       
        1502    LOAD_NAME                       5: time
        1504    LOAD_ATTR                       50: sleep
        1524    LOAD_NAME                       48: delay_time
        1526    CALL                            1
        1534    POP_TOP                         
        1536    JUMP_BACKWARD                   317 (to 906)
        1540    PUSH_EXC_INFO                   
        1542    WITH_EXCEPT_START               
        1544    POP_JUMP_IF_TRUE                1 (to 1548)
        1546    RERAISE                         2
        1548    POP_TOP                         
        1550    POP_EXCEPT                      
        1552    POP_TOP                         
        1554    POP_TOP                         
        1556    JUMP_BACKWARD                   482 (to 596)
        1560    COPY                            3
        1562    POP_EXCEPT                      
        1564    RERAISE                         1
        1566    PUSH_EXC_INFO                   
        1568    WITH_EXCEPT_START               
        1570    POP_JUMP_IF_TRUE                1 (to 1574)
        1572    RERAISE                         2
        1574    POP_TOP                         
        1576    POP_EXCEPT                      
        1578    POP_TOP                         
        1580    POP_TOP                         
        1582    JUMP_BACKWARD                   200 (to 1184)
        1584    COPY                            3
        1586    POP_EXCEPT                      
        1588    RERAISE                         1
        1590    PUSH_EXC_INFO                   
        1592    LOAD_NAME                       0: requests
        1594    LOAD_ATTR                       134: exceptions
        1614    LOAD_ATTR                       136: RequestException
        1634    CHECK_EXC_MATCH                 
        1636    POP_JUMP_IF_FALSE               85 (to 1808)
        1638    STORE_NAME                      69: e
        1640    PUSH_NULL                       
        1642    LOAD_NAME                       6: datetime
        1644    LOAD_ATTR                       130: now
        1664    CALL                            0
        1672    LOAD_ATTR                       61: strftime
        1692    LOAD_CONST                      12: '%Y-%m-%d %H:%M:%S'
        1694    CALL                            1
        1702    STORE_NAME                      66: current_time
        1704    PUSH_NULL                       
        1706    LOAD_NAME                       27: print
        1708    LOAD_CONST                      37: '\x1b[1;31m['
        1710    LOAD_NAME                       66: current_time
        1712    FORMAT_VALUE                    0
        1714    LOAD_CONST                      38: '] Internet disconnected. Reconnecting in 10 seconds...'
        1716    LOAD_NAME                       11: Style
        1718    LOAD_ATTR                       58: RESET_ALL
        1738    FORMAT_VALUE                    0
        1740    BUILD_STRING                    4
        1742    CALL                            1
        1750    POP_TOP                         
        1752    PUSH_NULL                       
        1754    LOAD_NAME                       5: time
        1756    LOAD_ATTR                       50: sleep
        1776    LOAD_CONST                      39: 10
        1778    CALL                            1
        1786    POP_TOP                         
        1788    POP_EXCEPT                      
        1790    LOAD_CONST                      1: None
        1792    STORE_NAME                      69: e
        1794    DELETE_NAME                     69: e
        1796    JUMP_BACKWARD                   435 (to 930)
        1800    LOAD_CONST                      1: None
        1802    STORE_NAME                      69: e
        1804    DELETE_NAME                     69: e
        1806    RERAISE                         1
        1808    LOAD_NAME                       70: Exception
        1810    CHECK_EXC_MATCH                 
        1812    POP_JUMP_IF_FALSE               75 (to 1964)
        1814    STORE_NAME                      69: e
        1816    PUSH_NULL                       
        1818    LOAD_NAME                       6: datetime
        1820    LOAD_ATTR                       130: now
        1840    CALL                            0
        1848    LOAD_ATTR                       61: strftime
        1868    LOAD_CONST                      12: '%Y-%m-%d %H:%M:%S'
        1870    CALL                            1
        1878    STORE_NAME                      66: current_time
        1880    PUSH_NULL                       
        1882    LOAD_NAME                       27: print
        1884    LOAD_CONST                      37: '\x1b[1;31m['
        1886    LOAD_NAME                       66: current_time
        1888    FORMAT_VALUE                    0
        1890    LOAD_CONST                      40: '] An error occurred:➜ '
        1892    PUSH_NULL                       
        1894    LOAD_NAME                       71: str
        1896    LOAD_NAME                       69: e
        1898    CALL                            1
        1906    FORMAT_VALUE                    0
        1908    LOAD_NAME                       11: Style
        1910    LOAD_ATTR                       58: RESET_ALL
        1930    FORMAT_VALUE                    0
        1932    BUILD_STRING                    5
        1934    CALL                            1
        1942    POP_TOP                         
        1944    POP_EXCEPT                      
        1946    LOAD_CONST                      1: None
        1948    STORE_NAME                      69: e
        1950    DELETE_NAME                     69: e
        1952    JUMP_BACKWARD                   513 (to 930)
        1956    LOAD_CONST                      1: None
        1958    STORE_NAME                      69: e
        1960    DELETE_NAME                     69: e
        1962    RERAISE                         1
        1964    RERAISE                         0
        1966    COPY                            3
        1968    POP_EXCEPT                      
        1970    RERAISE                         1
